MANIFEST.in
requirements.txt
setup.py
django_stampu.egg-info/PKG-INFO
django_stampu.egg-info/SOURCES.txt
django_stampu.egg-info/dependency_links.txt
django_stampu.egg-info/not-zip-safe
django_stampu.egg-info/requires.txt
django_stampu.egg-info/top_level.txt
stampu/__init__.py
stampu/settings.py
stampu/utils.py
stampu/management/__init__.py
stampu/management/commands/__init__.py
stampu/management/commands/stamp.py
stampu/renderers/__init__.py
stampu/renderers/disk.py