Metadata-Version: 1.1
Name: django-stampu
Version: 0.1.3
Summary: Convert your django sites into static content
Home-page: http://github.com/fmartingr/django-stampu
Author: Felipe Martin
Author-email: fmartingr@me.com
License: GPLv2
Platform: UNKNOWN
Classifier: Development Status :: 5 - Production/Stable
Classifier: Intended Audience :: Developers
Classifier: Operating System :: OS Independent
Classifier: Programming Language :: Python
